[{"RawFeatureName": "Application Type", "TypeDetected": "Categorical", "Dropped": "No", "EngineeredFeatureCount": 1, "Transformations": ["ModeCatImputer-StringCast-LabelEncoder"], "TransformationParams": {"Transformer1": {"Input": ["Application Type"], "TransformationFunction": "CatImputer", "Operator": "Mode", "FeatureType": "Categorical", "ShouldOutput": true, "TransformationParams": {"copy": true}}, "Transformer2": {"Input": ["Transformer1"], "TransformationFunction": "StringCast", "Operator": null, "FeatureType": null, "ShouldOutput": false, "TransformationParams": {}}, "Transformer3": {"Input": ["Transformer2"], "TransformationFunction": "LabelEncoder", "Operator": null, "FeatureType": null, "ShouldOutput": true, "TransformationParams": {"hashing_seed_val": 314489979}}}}, {"RawFeatureName": "Batch Enrolled", "TypeDetected": "Categorical", "Dropped": "No", "EngineeredFeatureCount": 41, "Transformations": ["StringCast-CharGramCountVectorizer"], "TransformationParams": {"Transformer1": {"Input": ["Batch Enrolled"], "TransformationFunction": "StringCast", "Operator": null, "FeatureType": "Categorical", "ShouldOutput": false, "TransformationParams": {}}, "Transformer2": {"Input": ["Transformer1"], "TransformationFunction": "CountVectorizer", "Operator": "CharGram", "FeatureType": null, "ShouldOutput": true, "TransformationParams": {"analyzer": "word", "binary": true, "decode_error": "strict", "encoding": "utf-8", "input": "content", "lowercase": true, "max_df": 1.0, "max_features": null, "min_df": 1, "ngram_range": [1, 1], "stop_words": null, "strip_accents": null, "token_pattern": "(?u)\\b\\w\\w+\\b", "vocabulary": null}}}}, {"RawFeatureName": "Collection 12 months Medical", "TypeDetected": "Categorical", "Dropped": "No", "EngineeredFeatureCount": 1, "Transformations": ["ModeCatImputer-StringCast-LabelEncoder"], "TransformationParams": {"Transformer1": {"Input": ["Collection 12 months Medical"], "TransformationFunction": "CatImputer", "Operator": "Mode", "FeatureType": "Categorical", "ShouldOutput": true, "TransformationParams": {"copy": true}}, "Transformer2": {"Input": ["Transformer1"], "TransformationFunction": "StringCast", "Operator": null, "FeatureType": null, "ShouldOutput": false, "TransformationParams": {}}, "Transformer3": {"Input": ["Transformer2"], "TransformationFunction": "LabelEncoder", "Operator": null, "FeatureType": null, "ShouldOutput": true, "TransformationParams": {"hashing_seed_val": 314489979}}}}, {"RawFeatureName": "Delinquency - two years", "TypeDetected": "Categorical", "Dropped": "No", "EngineeredFeatureCount": 9, "Transformations": ["StringCast-CharGramCountVectorizer"], "TransformationParams": {"Transformer1": {"Input": ["Delinquency - two years"], "TransformationFunction": "StringCast", "Operator": null, "FeatureType": "Categorical", "ShouldOutput": false, "TransformationParams": {}}, "Transformer2": {"Input": ["Transformer1"], "TransformationFunction": "CountVectorizer", "Operator": "CharGram", "FeatureType": null, "ShouldOutput": true, "TransformationParams": {"analyzer": "word", "binary": true, "decode_error": "strict", "encoding": "utf-8", "input": "content", "lowercase": true, "max_df": 1.0, "max_features": null, "min_df": 1, "ngram_range": [1, 1], "stop_words": null, "strip_accents": null, "token_pattern": "(?u)\\b\\w\\w+\\b", "vocabulary": null}}}}, {"RawFeatureName": "Employment Duration", "TypeDetected": "Categorical", "Dropped": "No", "EngineeredFeatureCount": 3, "Transformations": ["StringCast-CharGramCountVectorizer"], "TransformationParams": {"Transformer1": {"Input": ["Employment Duration"], "TransformationFunction": "StringCast", "Operator": null, "FeatureType": "Categorical", "ShouldOutput": false, "TransformationParams": {}}, "Transformer2": {"Input": ["Transformer1"], "TransformationFunction": "CountVectorizer", "Operator": "CharGram", "FeatureType": null, "ShouldOutput": true, "TransformationParams": {"analyzer": "word", "binary": true, "decode_error": "strict", "encoding": "utf-8", "input": "content", "lowercase": true, "max_df": 1.0, "max_features": null, "min_df": 1, "ngram_range": [1, 1], "stop_words": null, "strip_accents": null, "token_pattern": "(?u)\\b\\w\\w+\\b", "vocabulary": null}}}}, {"RawFeatureName": "Grade", "TypeDetected": "Categorical", "Dropped": "No", "EngineeredFeatureCount": 7, "Transformations": ["StringCast-CharGramCountVectorizer"], "TransformationParams": {"Transformer1": {"Input": ["Grade"], "TransformationFunction": "StringCast", "Operator": null, "FeatureType": "Categorical", "ShouldOutput": false, "TransformationParams": {}}, "Transformer2": {"Input": ["Transformer1"], "TransformationFunction": "CountVectorizer", "Operator": "CharGram", "FeatureType": null, "ShouldOutput": true, "TransformationParams": {"analyzer": "word", "binary": true, "decode_error": "strict", "encoding": "utf-8", "input": "content", "lowercase": true, "max_df": 1.0, "max_features": null, "min_df": 1, "ngram_range": [1, 1], "stop_words": null, "strip_accents": null, "token_pattern": "(?u)\\b\\w\\w+\\b", "vocabulary": null}}}}, {"RawFeatureName": "Initial List Status", "TypeDetected": "Categorical", "Dropped": "No", "EngineeredFeatureCount": 1, "Transformations": ["ModeCatImputer-StringCast-LabelEncoder"], "TransformationParams": {"Transformer1": {"Input": ["Initial List Status"], "TransformationFunction": "CatImputer", "Operator": "Mode", "FeatureType": "Categorical", "ShouldOutput": true, "TransformationParams": {"copy": true}}, "Transformer2": {"Input": ["Transformer1"], "TransformationFunction": "StringCast", "Operator": null, "FeatureType": null, "ShouldOutput": false, "TransformationParams": {}}, "Transformer3": {"Input": ["Transformer2"], "TransformationFunction": "LabelEncoder", "Operator": null, "FeatureType": null, "ShouldOutput": true, "TransformationParams": {"hashing_seed_val": 314489979}}}}, {"RawFeatureName": "Inquires - six months", "TypeDetected": "Categorical", "Dropped": "No", "EngineeredFeatureCount": 6, "Transformations": ["StringCast-CharGramCountVectorizer"], "TransformationParams": {"Transformer1": {"Input": ["Inquires - six months"], "TransformationFunction": "StringCast", "Operator": null, "FeatureType": "Categorical", "ShouldOutput": false, "TransformationParams": {}}, "Transformer2": {"Input": ["Transformer1"], "TransformationFunction": "CountVectorizer", "Operator": "CharGram", "FeatureType": null, "ShouldOutput": true, "TransformationParams": {"analyzer": "word", "binary": true, "decode_error": "strict", "encoding": "utf-8", "input": "content", "lowercase": true, "max_df": 1.0, "max_features": null, "min_df": 1, "ngram_range": [1, 1], "stop_words": null, "strip_accents": null, "token_pattern": "(?u)\\b\\w\\w+\\b", "vocabulary": null}}}}, {"RawFeatureName": "Open Account", "TypeDetected": "Categorical", "Dropped": "No", "EngineeredFeatureCount": 36, "Transformations": ["StringCast-CharGramCountVectorizer"], "TransformationParams": {"Transformer1": {"Input": ["Open Account"], "TransformationFunction": "StringCast", "Operator": null, "FeatureType": "Categorical", "ShouldOutput": false, "TransformationParams": {}}, "Transformer2": {"Input": ["Transformer1"], "TransformationFunction": "CountVectorizer", "Operator": "CharGram", "FeatureType": null, "ShouldOutput": true, "TransformationParams": {"analyzer": "word", "binary": true, "decode_error": "strict", "encoding": "utf-8", "input": "content", "lowercase": true, "max_df": 1.0, "max_features": null, "min_df": 1, "ngram_range": [1, 1], "stop_words": null, "strip_accents": null, "token_pattern": "(?u)\\b\\w\\w+\\b", "vocabulary": null}}}}, {"RawFeatureName": "Public Record", "TypeDetected": "Categorical", "Dropped": "No", "EngineeredFeatureCount": 5, "Transformations": ["StringCast-CharGramCountVectorizer"], "TransformationParams": {"Transformer1": {"Input": ["Public Record"], "TransformationFunction": "StringCast", "Operator": null, "FeatureType": "Categorical", "ShouldOutput": false, "TransformationParams": {}}, "Transformer2": {"Input": ["Transformer1"], "TransformationFunction": "CountVectorizer", "Operator": "CharGram", "FeatureType": null, "ShouldOutput": true, "TransformationParams": {"analyzer": "word", "binary": true, "decode_error": "strict", "encoding": "utf-8", "input": "content", "lowercase": true, "max_df": 1.0, "max_features": null, "min_df": 1, "ngram_range": [1, 1], "stop_words": null, "strip_accents": null, "token_pattern": "(?u)\\b\\w\\w+\\b", "vocabulary": null}}}}, {"RawFeatureName": "Sub Grade", "TypeDetected": "Categorical", "Dropped": "No", "EngineeredFeatureCount": 33, "Transformations": ["StringCast-CharGramCountVectorizer"], "TransformationParams": {"Transformer1": {"Input": ["Sub Grade"], "TransformationFunction": "StringCast", "Operator": null, "FeatureType": "Categorical", "ShouldOutput": false, "TransformationParams": {}}, "Transformer2": {"Input": ["Transformer1"], "TransformationFunction": "CountVectorizer", "Operator": "CharGram", "FeatureType": null, "ShouldOutput": true, "TransformationParams": {"analyzer": "word", "binary": true, "decode_error": "strict", "encoding": "utf-8", "input": "content", "lowercase": true, "max_df": 1.0, "max_features": null, "min_df": 1, "ngram_range": [1, 1], "stop_words": null, "strip_accents": null, "token_pattern": "(?u)\\b\\w\\w+\\b", "vocabulary": null}}}}, {"RawFeatureName": "Term", "TypeDetected": "Categorical", "Dropped": "No", "EngineeredFeatureCount": 3, "Transformations": ["StringCast-CharGramCountVectorizer"], "TransformationParams": {"Transformer1": {"Input": ["Term"], "TransformationFunction": "StringCast", "Operator": null, "FeatureType": "Categorical", "ShouldOutput": false, "TransformationParams": {}}, "Transformer2": {"Input": ["Transformer1"], "TransformationFunction": "CountVectorizer", "Operator": "CharGram", "FeatureType": null, "ShouldOutput": true, "TransformationParams": {"analyzer": "word", "binary": true, "decode_error": "strict", "encoding": "utf-8", "input": "content", "lowercase": true, "max_df": 1.0, "max_features": null, "min_df": 1, "ngram_range": [1, 1], "stop_words": null, "strip_accents": null, "token_pattern": "(?u)\\b\\w\\w+\\b", "vocabulary": null}}}}, {"RawFeatureName": "Verification Status", "TypeDetected": "Categorical", "Dropped": "No", "EngineeredFeatureCount": 3, "Transformations": ["StringCast-CharGramCountVectorizer"], "TransformationParams": {"Transformer1": {"Input": ["Verification Status"], "TransformationFunction": "StringCast", "Operator": null, "FeatureType": "Categorical", "ShouldOutput": false, "TransformationParams": {}}, "Transformer2": {"Input": ["Transformer1"], "TransformationFunction": "CountVectorizer", "Operator": "CharGram", "FeatureType": null, "ShouldOutput": true, "TransformationParams": {"analyzer": "word", "binary": true, "decode_error": "strict", "encoding": "utf-8", "input": "content", "lowercase": true, "max_df": 1.0, "max_features": null, "min_df": 1, "ngram_range": [1, 1], "stop_words": null, "strip_accents": null, "token_pattern": "(?u)\\b\\w\\w+\\b", "vocabulary": null}}}}, {"RawFeatureName": "Collection Recovery Fee", "TypeDetected": "Numeric", "Dropped": "No", "EngineeredFeatureCount": 1, "Transformations": ["MeanImputer"], "TransformationParams": {"Transformer1": {"Input": ["Collection Recovery Fee"], "TransformationFunction": "Imputer", "Operator": "Mean", "FeatureType": "Numeric", "ShouldOutput": true, "TransformationParams": {"add_indicator": false, "copy": true, "fill_value": null, "missing_values": NaN, "strategy": "mean", "verbose": 0}}}}, {"RawFeatureName": "Debit to Income", "TypeDetected": "Numeric", "Dropped": "No", "EngineeredFeatureCount": 1, "Transformations": ["MeanImputer"], "TransformationParams": {"Transformer1": {"Input": ["Debit to Income"], "TransformationFunction": "Imputer", "Operator": "Mean", "FeatureType": "Numeric", "ShouldOutput": true, "TransformationParams": {"add_indicator": false, "copy": true, "fill_value": null, "missing_values": NaN, "strategy": "mean", "verbose": 0}}}}, {"RawFeatureName": "Funded Amount", "TypeDetected": "Numeric", "Dropped": "No", "EngineeredFeatureCount": 1, "Transformations": ["MeanImputer"], "TransformationParams": {"Transformer1": {"Input": ["Funded Amount"], "TransformationFunction": "Imputer", "Operator": "Mean", "FeatureType": "Numeric", "ShouldOutput": true, "TransformationParams": {"add_indicator": false, "copy": true, "fill_value": null, "missing_values": NaN, "strategy": "mean", "verbose": 0}}}}, {"RawFeatureName": "Funded Amount Investor", "TypeDetected": "Numeric", "Dropped": "No", "EngineeredFeatureCount": 1, "Transformations": ["MeanImputer"], "TransformationParams": {"Transformer1": {"Input": ["Funded Amount Investor"], "TransformationFunction": "Imputer", "Operator": "Mean", "FeatureType": "Numeric", "ShouldOutput": true, "TransformationParams": {"add_indicator": false, "copy": true, "fill_value": null, "missing_values": NaN, "strategy": "mean", "verbose": 0}}}}, {"RawFeatureName": "Home Ownership", "TypeDetected": "Numeric", "Dropped": "No", "EngineeredFeatureCount": 1, "Transformations": ["MeanImputer"], "TransformationParams": {"Transformer1": {"Input": ["Home Ownership"], "TransformationFunction": "Imputer", "Operator": "Mean", "FeatureType": "Numeric", "ShouldOutput": true, "TransformationParams": {"add_indicator": false, "copy": true, "fill_value": null, "missing_values": NaN, "strategy": "mean", "verbose": 0}}}}, {"RawFeatureName": "Interest Rate", "TypeDetected": "Numeric", "Dropped": "No", "EngineeredFeatureCount": 1, "Transformations": ["MeanImputer"], "TransformationParams": {"Transformer1": {"Input": ["Interest Rate"], "TransformationFunction": "Imputer", "Operator": "Mean", "FeatureType": "Numeric", "ShouldOutput": true, "TransformationParams": {"add_indicator": false, "copy": true, "fill_value": null, "missing_values": NaN, "strategy": "mean", "verbose": 0}}}}, {"RawFeatureName": "Last week Pay", "TypeDetected": "Numeric", "Dropped": "No", "EngineeredFeatureCount": 1, "Transformations": ["MeanImputer"], "TransformationParams": {"Transformer1": {"Input": ["Last week Pay"], "TransformationFunction": "Imputer", "Operator": "Mean", "FeatureType": "Numeric", "ShouldOutput": true, "TransformationParams": {"add_indicator": false, "copy": true, "fill_value": null, "missing_values": NaN, "strategy": "mean", "verbose": 0}}}}, {"RawFeatureName": "Loan Amount", "TypeDetected": "Numeric", "Dropped": "No", "EngineeredFeatureCount": 1, "Transformations": ["MeanImputer"], "TransformationParams": {"Transformer1": {"Input": ["Loan Amount"], "TransformationFunction": "Imputer", "Operator": "Mean", "FeatureType": "Numeric", "ShouldOutput": true, "TransformationParams": {"add_indicator": false, "copy": true, "fill_value": null, "missing_values": NaN, "strategy": "mean", "verbose": 0}}}}, {"RawFeatureName": "Loan Title", "TypeDetected": "Numeric", "Dropped": "No", "EngineeredFeatureCount": 1, "Transformations": ["MeanImputer"], "TransformationParams": {"Transformer1": {"Input": ["Loan Title"], "TransformationFunction": "Imputer", "Operator": "Mean", "FeatureType": "Numeric", "ShouldOutput": true, "TransformationParams": {"add_indicator": false, "copy": true, "fill_value": null, "missing_values": NaN, "strategy": "mean", "verbose": 0}}}}, {"RawFeatureName": "Recoveries", "TypeDetected": "Numeric", "Dropped": "No", "EngineeredFeatureCount": 1, "Transformations": ["MeanImputer"], "TransformationParams": {"Transformer1": {"Input": ["Recoveries"], "TransformationFunction": "Imputer", "Operator": "Mean", "FeatureType": "Numeric", "ShouldOutput": true, "TransformationParams": {"add_indicator": false, "copy": true, "fill_value": null, "missing_values": NaN, "strategy": "mean", "verbose": 0}}}}, {"RawFeatureName": "Revolving Balance", "TypeDetected": "Numeric", "Dropped": "No", "EngineeredFeatureCount": 1, "Transformations": ["MeanImputer"], "TransformationParams": {"Transformer1": {"Input": ["Revolving Balance"], "TransformationFunction": "Imputer", "Operator": "Mean", "FeatureType": "Numeric", "ShouldOutput": true, "TransformationParams": {"add_indicator": false, "copy": true, "fill_value": null, "missing_values": NaN, "strategy": "mean", "verbose": 0}}}}, {"RawFeatureName": "Revolving Utilities", "TypeDetected": "Numeric", "Dropped": "No", "EngineeredFeatureCount": 1, "Transformations": ["MeanImputer"], "TransformationParams": {"Transformer1": {"Input": ["Revolving Utilities"], "TransformationFunction": "Imputer", "Operator": "Mean", "FeatureType": "Numeric", "ShouldOutput": true, "TransformationParams": {"add_indicator": false, "copy": true, "fill_value": null, "missing_values": NaN, "strategy": "mean", "verbose": 0}}}}, {"RawFeatureName": "Total Accounts", "TypeDetected": "Numeric", "Dropped": "No", "EngineeredFeatureCount": 1, "Transformations": ["MeanImputer"], "TransformationParams": {"Transformer1": {"Input": ["Total Accounts"], "TransformationFunction": "Imputer", "Operator": "Mean", "FeatureType": "Numeric", "ShouldOutput": true, "TransformationParams": {"add_indicator": false, "copy": true, "fill_value": null, "missing_values": NaN, "strategy": "mean", "verbose": 0}}}}, {"RawFeatureName": "Total Collection Amount", "TypeDetected": "Numeric", "Dropped": "No", "EngineeredFeatureCount": 1, "Transformations": ["MeanImputer"], "TransformationParams": {"Transformer1": {"Input": ["Total Collection Amount"], "TransformationFunction": "Imputer", "Operator": "Mean", "FeatureType": "Numeric", "ShouldOutput": true, "TransformationParams": {"add_indicator": false, "copy": true, "fill_value": null, "missing_values": NaN, "strategy": "mean", "verbose": 0}}}}, {"RawFeatureName": "Total Current Balance", "TypeDetected": "Numeric", "Dropped": "No", "EngineeredFeatureCount": 1, "Transformations": ["MeanImputer"], "TransformationParams": {"Transformer1": {"Input": ["Total Current Balance"], "TransformationFunction": "Imputer", "Operator": "Mean", "FeatureType": "Numeric", "ShouldOutput": true, "TransformationParams": {"add_indicator": false, "copy": true, "fill_value": null, "missing_values": NaN, "strategy": "mean", "verbose": 0}}}}, {"RawFeatureName": "Total Received Interest", "TypeDetected": "Numeric", "Dropped": "No", "EngineeredFeatureCount": 1, "Transformations": ["MeanImputer"], "TransformationParams": {"Transformer1": {"Input": ["Total Received Interest"], "TransformationFunction": "Imputer", "Operator": "Mean", "FeatureType": "Numeric", "ShouldOutput": true, "TransformationParams": {"add_indicator": false, "copy": true, "fill_value": null, "missing_values": NaN, "strategy": "mean", "verbose": 0}}}}, {"RawFeatureName": "Total Received Late Fee", "TypeDetected": "Numeric", "Dropped": "No", "EngineeredFeatureCount": 1, "Transformations": ["MeanImputer"], "TransformationParams": {"Transformer1": {"Input": ["Total Received Late Fee"], "TransformationFunction": "Imputer", "Operator": "Mean", "FeatureType": "Numeric", "ShouldOutput": true, "TransformationParams": {"add_indicator": false, "copy": true, "fill_value": null, "missing_values": NaN, "strategy": "mean", "verbose": 0}}}}, {"RawFeatureName": "Total Revolving Credit Limit", "TypeDetected": "Numeric", "Dropped": "No", "EngineeredFeatureCount": 1, "Transformations": ["MeanImputer"], "TransformationParams": {"Transformer1": {"Input": ["Total Revolving Credit Limit"], "TransformationFunction": "Imputer", "Operator": "Mean", "FeatureType": "Numeric", "ShouldOutput": true, "TransformationParams": {"add_indicator": false, "copy": true, "fill_value": null, "missing_values": NaN, "strategy": "mean", "verbose": 0}}}}]